cnxml/__init__.py
cnxml/_version.py
cnxml/cli.py
cnxml/jing.jar
cnxml/jing.py
cnxml/parse.py
cnxml/util.py
cnxml/validation.py
cnxml/tests/__init__.py
cnxml/tests/conftest.py
cnxml/tests/test_cli.py
cnxml/tests/test_jing.py
cnxml/tests/test_parse.py
cnxml/tests/test_util.py
cnxml/tests/test_validation.py
cnxml/tests/data/jing/invalid.xml
cnxml/tests/data/jing/test.rng
cnxml/tests/data/jing/valid.xml
cnxml/xml/bibtexml/catalog.sgml
cnxml/xml/bibtexml/catalog.xml
cnxml/xml/bibtexml/schema/dtd/1.0/bibteXML-ext-modular.dtd
cnxml/xml/bibtexml/schema/dtd/1.0/bibteXML.dtd
cnxml/xml/bibtexml/schema/rng/1.0/bibtexml.rng
cnxml/xml/bibtexml/schema/xsd/1.0/bibteXML.xsd
cnxml/xml/bibtexml/stylesheet/bibtexml.xsl
cnxml/xml/cnxml/catalog-0.7.sgml
cnxml/xml/cnxml/catalog-0.7.xml
cnxml/xml/cnxml/catalog-common.sgml
cnxml/xml/cnxml/catalog-common.xml
cnxml/xml/cnxml/schema/rng/0.7/cnxml-abstract-defs.rng
cnxml/xml/cnxml/schema/rng/0.7/cnxml-abstract-driver.rng
cnxml/xml/cnxml/schema/rng/0.7/cnxml-common-jing.rng
cnxml/xml/cnxml/schema/rng/0.7/cnxml-common.rng
cnxml/xml/cnxml/schema/rng/0.7/cnxml-defs.rng
cnxml/xml/cnxml/schema/rng/0.7/cnxml-fragment-jing.rng
cnxml/xml/cnxml/schema/rng/0.7/cnxml-jing.rng
cnxml/xml/cnxml/schema/rng/0.7/cnxml-simplified.rng
cnxml/xml/cnxml/schema/rng/0.7/cnxml.rng
cnxml/xml/cnxml/stylesheet/cnxml05to06.xsl
cnxml/xml/cnxml/stylesheet/cnxml06to07.xsl
cnxml/xml/cnxml/stylesheet/cnxml_render.xsl
cnxml/xml/cnxml/stylesheet/cnxmll10n.xsl
cnxml/xml/cnxml/stylesheet/ident.xsl
cnxml/xml/cnxml/stylesheet/l10n.xml
cnxml/xml/cnxml/stylesheet/media.xsl
cnxml/xml/cnxml/stylesheet/memcases.xml
cnxml/xml/cnxml/stylesheet/table.xsl
cnxml/xml/collxml/connexions-collxml-1.0.xml
cnxml/xml/collxml/schema/rng/1.0/collxml-defs.rng
cnxml/xml/collxml/schema/rng/1.0/collxml-jing.rng
cnxml/xml/collxml/schema/rng/1.0/collxml-simplified.rng
cnxml/xml/collxml/schema/rng/1.0/collxml.rng
cnxml/xml/collxml/schema/rng/2.0/collxml-defs.rng
cnxml-3.1.9.dist-info/LICENSE.txt
cnxml-3.1.9.dist-info/METADATA
cnxml-3.1.9.dist-info/WHEEL
cnxml-3.1.9.dist-info/entry_points.txt
cnxml-3.1.9.dist-info/top_level.txt
cnxml-3.1.9.dist-info/RECORD
