Metadata-Version: 2.1
Name: cnxml
Version: 3.1.9
Summary: Connexions CNXML Library
Home-page: https://github.com/connexions/cnxml
Author: Connexions team
Author-email: info@cnx.org
License: AGPL, See also LICENSE.txt
Platform: UNKNOWN
License-File: LICENSE.txt
Requires-Dist: lxml
Provides-Extra: test
Requires-Dist: pytest ; extra == 'test'
